matsushiba_db/__init__.py
matsushiba_db/async_client.py
matsushiba_db/cli.py
matsushiba_db/client.py
matsushiba_db/enhanced_client.py
matsushiba_db/init.py
matsushiba_db/internal_abstraction.py
matsushiba_db/server.py
matsushiba_db/welcome.py
matsushibadb-1.0.9.dist-info/licenses/LICENSE
matsushibadb-1.0.9.dist-info/METADATA
matsushibadb-1.0.9.dist-info/WHEEL
matsushibadb-1.0.9.dist-info/entry_points.txt
matsushibadb-1.0.9.dist-info/top_level.txt
matsushibadb-1.0.9.dist-info/RECORD
