Metadata-Version: 2.4
Name: matsushibadb
Version: 1.0.9
Summary: MatsushibaDB - Next-Generation SQL Database with Local Support, Caching, and Async/Await
Home-page: https://db.matsushiba.co
Author: Matsushiba Systems
Author-email: Matsushiba Systems <support@matsushiba.co>
Maintainer-email: Matsushiba Systems <support@matsushiba.co>
License: Commercial
Project-URL: Homepage, https://db.matsushiba.co
Project-URL: Documentation, https://db.matsushiba.co/docs
Project-URL: Repository, https://github.com/matsushibaco/matsushibadb
Project-URL: Bug Reports, https://github.com/matsushibaco/matsushibadb/issues
Keywords: database,sqlite,server,api,web,high-performance,self-contained,enterprise,security,rbac,audit,encryption
Classifier: Development Status :: 5 - Production/Stable
Classifier: Intended Audience :: Developers
Classifier: Intended Audience :: System Administrators
Classifier: Topic :: Database
Classifier: Topic :: Software Development :: Libraries :: Python Modules
Classifier: License :: Other/Proprietary License
Classifier: Programming Language :: Python :: 3
Classifier: Programming Language :: Python :: 3.8
Classifier: Programming Language :: Python :: 3.9
Classifier: Programming Language :: Python :: 3.10
Classifier: Programming Language :: Python :: 3.11
Classifier: Programming Language :: Python :: 3.12
Classifier: Operating System :: OS Independent
Requires-Python: >=3.8
License-File: LICENSE
Requires-Dist: requests>=2.31.0
Requires-Dist: websockets>=11.0.0
Requires-Dist: flask>=2.3.0
Requires-Dist: flask-cors>=4.0.0
Requires-Dist: flask-limiter>=3.0.0
Requires-Dist: cryptography>=41.0.0
Requires-Dist: PyJWT>=2.8.0
Requires-Dist: bcrypt>=4.0.0
Requires-Dist: aiohttp>=3.8.0
Requires-Dist: psutil>=5.9.0
Requires-Dist: pyyaml>=6.0
Requires-Dist: colorlog>=6.7.0
Provides-Extra: dev
Requires-Dist: pytest>=7.0.0; extra == "dev"
Requires-Dist: pytest-cov>=4.0.0; extra == "dev"
Requires-Dist: black>=23.0.0; extra == "dev"
Requires-Dist: flake8>=6.0.0; extra == "dev"
Requires-Dist: mypy>=1.0.0; extra == "dev"
Provides-Extra: async
Requires-Dist: aiohttp>=3.8.0; extra == "async"
Requires-Dist: websockets>=11.0.0; extra == "async"
Provides-Extra: server
Requires-Dist: flask>=2.3.0; extra == "server"
Requires-Dist: flask-cors>=4.0.0; extra == "server"
Requires-Dist: flask-limiter>=3.0.0; extra == "server"
Requires-Dist: cryptography>=41.0.0; extra == "server"
Requires-Dist: PyJWT>=2.8.0; extra == "server"
Requires-Dist: bcrypt>=4.0.0; extra == "server"
Dynamic: author
Dynamic: home-page
Dynamic: license-file
Dynamic: requires-python
